{
    "statistics": {
        "address1": "801 East 86th Avenue",
        "city": "Merrillville",
        "state": "IN",
        "zip": "46410",
        "country": "United States",
        "phone": "877 647 5990",
        "website": "https://www.nisource.com",
        "industry": "Utilities - Regulated Gas",
        "industryKey": "utilities-regulated-gas",
        "industryDisp": "Utilities - Regulated Gas",
        "sector": "Utilities",
        "sectorKey": "utilities",
        "sectorDisp": "Utilities",
        "longBusinessSummary": "NiSource Inc., an energy holding company, operates as a regulated natural gas and electric utility company in the United States. It operates in two segments, Gas Distribution Operations and Electric Operations. The company distributes natural gas to approximately 3.3 million customers through approximately 55,000 miles of distribution main pipeline and the associated individual customer service lines; and 1,000 miles of transmission main pipeline in northern Indiana, Ohio, Pennsylvania, Virginia, Kentucky, and Maryland. It also generates, transmits, and distributes electricity to approximately 0.5 million customers in various counties in the northern part of Indiana, as well as engages in wholesale electric and transmission transactions. It owns and operates coal-fired electric generating stations in Wheatfield and Michigan City; combined cycle gas turbine in West Terre Haute; natural gas generating units in Wheatfield; hydro generating plants in Carroll County and White County; wind generating units in White County, Indiana; and solar generating units in Jasper County and White County. The company was formerly known as NIPSCO Industries, Inc. and changed its name to NiSource Inc. in April 1999. NiSource Inc. was founded in 1847 and is headquartered in Merrillville, Indiana.",
        "fullTimeEmployees": 7364,
        "companyOfficers": [
            {
                "maxAge": 1,
                "name": "Mr. Lloyd M. Yates",
                "age": 62,
                "title": "President, CEO & Director",
                "yearBorn": 1961,
                "fiscalYear": 2023,
                "totalPay": 4008259,
                "exercisedValue": 0,
                "unexercisedValue": 0
            },
            {
                "maxAge": 1,
                "name": "Mr. Shawn  Anderson",
                "age": 41,
                "title": "Executive VP & CFO",
                "yearBorn": 1982,
                "fiscalYear": 2023,
                "totalPay": 1423643,
                "exercisedValue": 0,
                "unexercisedValue": 0
            },
            {
                "maxAge": 1,
                "name": "Mr. William  Jefferson Jr.",
                "age": 61,
                "title": "Executive VP & Chief Operating and Safety Officer",
                "yearBorn": 1962,
                "fiscalYear": 2023,
                "totalPay": 1438989,
                "exercisedValue": 0,
                "unexercisedValue": 0
            },
            {
                "maxAge": 1,
                "name": "Ms. Melody  Birmingham",
                "age": 51,
                "title": "Executive VP & Group President of Utilities",
                "yearBorn": 1972,
                "fiscalYear": 2023,
                "totalPay": 1572496,
                "exercisedValue": 0,
                "unexercisedValue": 0
            },
            {
                "maxAge": 1,
                "name": "Mr. Michael S. Luhrs",
                "age": 50,
                "title": "Executive VP of Strategy & Risk and Chief Commercial Officer",
                "yearBorn": 1973,
                "fiscalYear": 2023,
                "totalPay": 1482859,
                "exercisedValue": 0,
                "unexercisedValue": 0
            },
            {
                "maxAge": 1,
                "name": "Mr. Gunnar J. Gode",
                "age": 48,
                "title": "VP, Chief Accounting Officer & Controller",
                "yearBorn": 1975,
                "fiscalYear": 2023,
                "exercisedValue": 0,
                "unexercisedValue": 0
            },
            {
                "maxAge": 1,
                "name": "Ms. Melanie B. Berman",
                "age": 52,
                "title": "Chief Human Resources Officer & Senior VP of Administration",
                "yearBorn": 1971,
                "fiscalYear": 2023,
                "exercisedValue": 0,
                "unexercisedValue": 0
            },
            {
                "maxAge": 1,
                "name": "Ms. Kimberly S. Cuccia",
                "age": 39,
                "title": "Senior VP, General Counsel & Corporate Secretary",
                "yearBorn": 1984,
                "fiscalYear": 2023,
                "exercisedValue": 0,
                "unexercisedValue": 0
            },
            {
                "maxAge": 1,
                "name": "Mr. Mark  Kempic",
                "title": "President & COO of Columbia Gas of Pennsylvania and Maryland",
                "fiscalYear": 2023,
                "exercisedValue": 0,
                "unexercisedValue": 0
            },
            {
                "maxAge": 1,
                "name": "Mr. Vincent A. Parisi",
                "age": 55,
                "title": "President & COO of NIPSCO",
                "yearBorn": 1968,
                "fiscalYear": 2023,
                "exercisedValue": 0,
                "unexercisedValue": 0
            }
        ],
        "auditRisk": 4,
        "boardRisk": 2,
        "compensationRisk": 3,
        "shareHolderRightsRisk": 5,
        "overallRisk": 2,
        "governanceEpochDate": 1714521600,
        "compensationAsOfEpochDate": 1703980800,
        "irWebsite": "http://ir.nisource.com/index.cfm",
        "maxAge": 86400,
        "priceHint": 2,
        "previousClose": 28.87,
        "open": 28.72,
        "dayLow": 28.055,
        "dayHigh": 28.72,
        "regularMarketPreviousClose": 28.87,
        "regularMarketOpen": 28.72,
        "regularMarketDayLow": 28.055,
        "regularMarketDayHigh": 28.72,
        "dividendRate": 1.06,
        "dividendYield": 0.0367,
        "exDividendDate": 1722384000,
        "payoutRatio": 0.65910006,
        "fiveYearAvgDividendYield": 3.38,
        "beta": 0.481,
        "trailingPE": 18.233767,
        "forwardPE": 15.178378,
        "volume": 2880979,
        "regularMarketVolume": 2880979,
        "averageVolume": 4316259,
        "averageVolume10days": 4738950,
        "averageDailyVolume10Day": 4738950,
        "bid": 28.12,
        "ask": 28.11,
        "bidSize": 900,
        "askSize": 3000,
        "marketCap": 12588403712,
        "fiftyTwoWeekLow": 22.86,
        "fiftyTwoWeekHigh": 29.44,
        "priceToSalesTrailing12Months": 2.3997567,
        "fiftyDayAverage": 27.793,
        "twoHundredDayAverage": 26.50035,
        "trailingAnnualDividendRate": 1.03,
        "trailingAnnualDividendYield": 0.035677172,
        "currency": "USD",
        "enterpriseValue": 27710275584,
        "profitMargins": 0.14227,
        "floatShares": 446444871,
        "sharesOutstanding": 448304992,
        "sharesShort": 7636624,
        "sharesShortPriorMonth": 6073662,
        "sharesShortPreviousMonthDate": 1711584000,
        "dateShortInterest": 1714435200,
        "sharesPercentSharesOut": 0.017,
        "heldPercentInsiders": 0.0014300001,
        "heldPercentInstitutions": 0.95794,
        "shortRatio": 2.07,
        "shortPercentOfFloat": 0.0194,
        "impliedSharesOutstanding": 453584992,
        "bookValue": 17.617,
        "priceToBook": 1.5939149,
        "lastFiscalYearEnd": 1703980800,
        "nextFiscalYearEnd": 1735603200,
        "mostRecentQuarter": 1711843200,
        "earningsQuarterlyGrowth": 0.096,
        "netIncomeToCommon": 686700032,
        "trailingEps": 1.54,
        "forwardEps": 1.85,
        "pegRatio": 2.27,
        "lastSplitFactor": "2545:1000",
        "lastSplitDate": 1435795200,
        "enterpriseToRevenue": 5.282,
        "enterpriseToEbitda": 12.703,
        "52WeekChange": 0.06886339,
        "SandP52WeekChange": 0.27840328,
        "lastDividendValue": 0.265,
        "lastDividendDate": 1714348800,
        "exchange": "NYQ",
        "quoteType": "EQUITY",
        "symbol": "NI",
        "underlyingSymbol": "NI",
        "shortName": "NiSource Inc",
        "longName": "NiSource Inc.",
        "firstTradeDateEpochUtc": 99153000,
        "timeZoneFullName": "America/New_York",
        "timeZoneShortName": "EDT",
        "uuid": "fff6fa4f-e7dd-3c3a-931c-a45d9e626ae7",
        "messageBoardId": "finmb_53839770",
        "gmtOffSetMilliseconds": -14400000,
        "currentPrice": 28.08,
        "targetHighPrice": 34.0,
        "targetLowPrice": 27.0,
        "targetMeanPrice": 31.23,
        "targetMedianPrice": 31.0,
        "recommendationMean": 1.8,
        "recommendationKey": "buy",
        "numberOfAnalystOpinions": 11,
        "totalCash": 102200000,
        "totalCashPerShare": 0.228,
        "ebitda": 2181400064,
        "totalDebt": 12970900480,
        "quickRatio": 0.317,
        "currentRatio": 0.659,
        "totalRevenue": 5245700096,
        "debtToEquity": 132.425,
        "revenuePerShare": 12.346,
        "returnOnAssets": 0.02954,
        "returnOnEquity": 0.0828,
        "freeCashflow": -1658724992,
        "operatingCashflow": 1707900032,
        "earningsGrowth": 0.075,
        "revenueGrowth": -0.132,
        "grossMargins": 0.49216,
        "ebitdaMargins": 0.41584998,
        "operatingMargins": 0.34062,
        "financialCurrency": "USD",
        "trailingPegRatio": 1.8048
    }
}