{
    "statistics": {
        "address1": "1211 Avenue of the Americas",
        "city": "New York",
        "state": "NY",
        "zip": "10036",
        "country": "United States",
        "phone": "212 696 0100",
        "website": "https://www.annaly.com",
        "industry": "REIT - Mortgage",
        "industryKey": "reit-mortgage",
        "industryDisp": "REIT - Mortgage",
        "sector": "Real Estate",
        "sectorKey": "real-estate",
        "sectorDisp": "Real Estate",
        "longBusinessSummary": "Annaly Capital Management, Inc., a diversified capital manager, engages in mortgage finance. The company invests in agency mortgage-backed securities collateralized by residential mortgages; non-agency residential whole loans and securitized products within the residential and commercial markets; mortgage servicing rights; agency commercial mortgage-backed securities; to-be-announced forward contracts; residential mortgage loans; and agency or private label credit risk transfer securities. It has elected to be taxed as a real estate investment trust (REIT). As a REIT, it is not subject to federal income tax to the extent that it distributes its taxable income to its shareholders. The company was incorporated in 1996 and is based in New York, New York.",
        "fullTimeEmployees": 187,
        "companyOfficers": [
            {
                "maxAge": 1,
                "name": "Mr. David L. Finkelstein C.F.A.",
                "age": 50,
                "title": "CEO, Chief Investment Officer & Director",
                "yearBorn": 1973,
                "fiscalYear": 2023,
                "totalPay": 8343300,
                "exercisedValue": 0,
                "unexercisedValue": 0
            },
            {
                "maxAge": 1,
                "name": "Mr. Steven Francis Campbell",
                "age": 50,
                "title": "COO & President",
                "yearBorn": 1973,
                "fiscalYear": 2023,
                "totalPay": 3505000,
                "exercisedValue": 0,
                "unexercisedValue": 0
            },
            {
                "maxAge": 1,
                "name": "Ms. Serena  Wolfe",
                "age": 43,
                "title": "Chief Financial Officer",
                "yearBorn": 1980,
                "fiscalYear": 2023,
                "totalPay": 3112650,
                "exercisedValue": 0,
                "unexercisedValue": 0
            },
            {
                "maxAge": 1,
                "name": "Mr. Anthony Charles Green J.D.",
                "age": 48,
                "title": "Chief Corporate Officer, Chief Legal Officer & Secretary",
                "yearBorn": 1975,
                "fiscalYear": 2023,
                "totalPay": 2800500,
                "exercisedValue": 0,
                "unexercisedValue": 0
            },
            {
                "maxAge": 1,
                "name": "Ms. Audrey K. Susanin J.D.",
                "age": 41,
                "title": "Deputy General Counsel & Chief Compliance Officer",
                "yearBorn": 1982,
                "fiscalYear": 2023,
                "exercisedValue": 0,
                "unexercisedValue": 0
            },
            {
                "maxAge": 1,
                "name": "Ms. Seana Scott Gormley",
                "title": "Chief Human Resources Officer",
                "fiscalYear": 2023,
                "exercisedValue": 0,
                "unexercisedValue": 0
            },
            {
                "maxAge": 1,
                "name": "Ms. Jessica T. LaScala",
                "title": "Head of Investment Operations",
                "fiscalYear": 2023,
                "exercisedValue": 0,
                "unexercisedValue": 0
            },
            {
                "maxAge": 1,
                "name": "Mr. Michael  Fania",
                "title": "Deputy Chief Investment Officer & Head of Residential Credit",
                "fiscalYear": 2023,
                "exercisedValue": 0,
                "unexercisedValue": 0
            },
            {
                "maxAge": 1,
                "name": "Ms. Johanna  Griffin",
                "title": "Chief Risk Officer",
                "fiscalYear": 2023,
                "exercisedValue": 0,
                "unexercisedValue": 0
            },
            {
                "maxAge": 1,
                "name": "Ms. Tanya  Rakpraja",
                "title": "Head of Corporate Responsibility & Government Relations",
                "fiscalYear": 2023,
                "exercisedValue": 0,
                "unexercisedValue": 0
            }
        ],
        "auditRisk": 3,
        "boardRisk": 1,
        "compensationRisk": 6,
        "shareHolderRightsRisk": 3,
        "overallRisk": 2,
        "governanceEpochDate": 1714521600,
        "compensationAsOfEpochDate": 1703980800,
        "irWebsite": "http://investor.annaly.com/corporateprofile.aspx?iid=113558",
        "maxAge": 86400,
        "priceHint": 2,
        "previousClose": 19.89,
        "open": 19.89,
        "dayLow": 19.28,
        "dayHigh": 19.9,
        "regularMarketPreviousClose": 19.89,
        "regularMarketOpen": 19.89,
        "regularMarketDayLow": 19.28,
        "regularMarketDayHigh": 19.9,
        "dividendRate": 2.6,
        "dividendYield": 0.13069999,
        "exDividendDate": 1711497600,
        "payoutRatio": 0.898,
        "fiveYearAvgDividendYield": 13.35,
        "beta": 1.587,
        "forwardPE": 7.129151,
        "volume": 2946334,
        "regularMarketVolume": 2946334,
        "averageVolume": 3261693,
        "averageVolume10days": 2532800,
        "averageDailyVolume10Day": 2532800,
        "bid": 19.31,
        "ask": 19.69,
        "bidSize": 3000,
        "askSize": 900,
        "marketCap": 9668500480,
        "fiftyTwoWeekLow": 14.52,
        "fiftyTwoWeekHigh": 21.07,
        "priceToSalesTrailing12Months": -42.25817,
        "fiftyDayAverage": 19.3162,
        "twoHundredDayAverage": 18.9115,
        "trailingAnnualDividendRate": 2.6,
        "trailingAnnualDividendYield": 0.13071895,
        "currency": "USD",
        "enterpriseValue": 87689396224,
        "floatShares": 499178914,
        "sharesOutstanding": 500440000,
        "sharesShort": 9243674,
        "sharesShortPriorMonth": 9703960,
        "sharesShortPreviousMonthDate": 1711584000,
        "dateShortInterest": 1714435200,
        "sharesPercentSharesOut": 0.0185,
        "heldPercentInsiders": 0.00247,
        "heldPercentInstitutions": 0.54326,
        "shortRatio": 2.78,
        "shortPercentOfFloat": 0.0209,
        "impliedSharesOutstanding": 507484992,
        "bookValue": 19.729,
        "priceToBook": 0.9792691,
        "lastFiscalYearEnd": 1703980800,
        "nextFiscalYearEnd": 1735603200,
        "mostRecentQuarter": 1711843200,
        "netIncomeToCommon": -482884992,
        "trailingEps": -0.97,
        "forwardEps": 2.71,
        "pegRatio": -1.53,
        "lastSplitFactor": "1:4",
        "lastSplitDate": 1664150400,
        "enterpriseToRevenue": -383.265,
        "52WeekChange": 0.1180439,
        "SandP52WeekChange": 0.27840328,
        "lastDividendValue": 0.65,
        "lastDividendDate": 1711497600,
        "exchange": "NYQ",
        "quoteType": "EQUITY",
        "symbol": "NLY",
        "underlyingSymbol": "NLY",
        "shortName": "Annaly Capital Management Inc.",
        "longName": "Annaly Capital Management, Inc.",
        "firstTradeDateEpochUtc": 876317400,
        "timeZoneFullName": "America/New_York",
        "timeZoneShortName": "EDT",
        "uuid": "44108ffa-8fb0-3a68-991b-ac94c6e2ec38",
        "messageBoardId": "finmb_382914",
        "gmtOffSetMilliseconds": -14400000,
        "currentPrice": 19.32,
        "targetHighPrice": 22.0,
        "targetLowPrice": 19.0,
        "targetMeanPrice": 20.47,
        "targetMedianPrice": 20.75,
        "recommendationMean": 2.4,
        "recommendationKey": "buy",
        "numberOfAnalystOpinions": 8,
        "totalCash": 502112000,
        "totalCashPerShare": 1.003,
        "totalDebt": 76614615040,
        "quickRatio": 0.32,
        "currentRatio": 0.342,
        "totalRevenue": -228796000,
        "debtToEquity": 666.439,
        "revenuePerShare": -0.46,
        "returnOnAssets": -0.00375,
        "returnOnEquity": -0.02854,
        "operatingCashflow": 5084063744,
        "operatingMargins": 0.90529,
        "financialCurrency": "USD",
        "trailingPegRatio": null
    }
}